setup.py
hejing/__init__.py
hejing.egg-info/PKG-INFO
hejing.egg-info/SOURCES.txt
hejing.egg-info/dependency_links.txt
hejing.egg-info/not-zip-safe
hejing.egg-info/top_level.txt