Metadata-Version: 1.0
Name: hejing
Version: 0.1
Summary: clinical trial information retriver
Home-page: https://github.com/kobyant/clinicaltrial
Author: jing
Author-email: jinghedeveloper@163.com
License: MIT
Platform: UNKNOWN
